netbox_qbeyond_addon/__init__.py
netbox_qbeyond_addon/api/serializers.py
netbox_qbeyond_addon/api/urls.py
netbox_qbeyond_addon/api/views.py
netbox_qbeyond_addon/auth/__init__.py
netbox_qbeyond_addon/filters.py
netbox_qbeyond_addon/forms.py
netbox_qbeyond_addon/migrations/__init__.py
netbox_qbeyond_addon/navigation.py
netbox_qbeyond_addon/urls.py
netbox_qbeyond_addon/views.py
netbox_qbeyond_addon-1.1.0.dist-info/LICENSE.txt
netbox_qbeyond_addon-1.1.0.dist-info/METADATA
netbox_qbeyond_addon-1.1.0.dist-info/WHEEL
netbox_qbeyond_addon-1.1.0.dist-info/RECORD
